lexid/__init__.py
lexid/__main__.py
lexid-2021.1006.dist-info/LICENSE
lexid-2021.1006.dist-info/METADATA
lexid-2021.1006.dist-info/WHEEL
lexid-2021.1006.dist-info/entry_points.txt
lexid-2021.1006.dist-info/top_level.txt
lexid-2021.1006.dist-info/zip-safe
lexid-2021.1006.dist-info/RECORD
